.DS_Store
simple_s3fs/__init__.py
simple_s3fs/__main__.py
simple_s3fs/_version.py
simple_s3fs/httpfs.py
simple_s3fs-0.1.6.dist-info/LICENSE
simple_s3fs-0.1.6.dist-info/METADATA
simple_s3fs-0.1.6.dist-info/WHEEL
simple_s3fs-0.1.6.dist-info/entry_points.txt
simple_s3fs-0.1.6.dist-info/top_level.txt
simple_s3fs-0.1.6.dist-info/RECORD
