Metadata-Version: 2.1
Name: simple-s3fs
Version: 0.1.6
Summary: A simple FUSE filesystem for reading files in S3 buckets. Forked from https://github.com/higlass/simple-httpfs and has been adapted to the needs of the 4DN data portal.
Home-page: https://github.com/4dn-dcic/simple-s3fs
Author: Alexander Veit
Author-email: alexander_veit@hms.harvard.edu
License: MIT
Platform: UNKNOWN
Requires-Python: >=3.6
Requires-Dist: fusepy
Requires-Dist: requests
Requires-Dist: diskcache
Requires-Dist: numpy
Requires-Dist: boto3
Requires-Dist: slugid
